setup.py
bw2dataclient/__init__.py
bw2dataclient/client.py
bw2dataclient.egg-info/PKG-INFO
bw2dataclient.egg-info/SOURCES.txt
bw2dataclient.egg-info/dependency_links.txt
bw2dataclient.egg-info/not-zip-safe
bw2dataclient.egg-info/requires.txt
bw2dataclient.egg-info/top_level.txt