Metadata-Version: 1.0
Name: bw2dataclient
Version: 0.5
Summary: Simple wrapper for accessing data resources over BOSSWAVE
Home-page: https://github.com/gtfierro/pybw2dataclient
Author: Gabe Fierro
Author-email: gtfierro@cs.berkeley.edu
License: UNKNOWN
Platform: UNKNOWN
